dscontexai/__init__.py
dscontexai/dsc_grammar.py
dscontexai/dsc_ploting.py
dscontexai/dsc_xgboost.py
dscontexai/generate_report.py
dscontexai/grammar_with_box_latex.py
dscontexai/latex/neurips_2023.sty
dscontexai-1.1.0.dist-info/METADATA
dscontexai-1.1.0.dist-info/WHEEL
dscontexai-1.1.0.dist-info/top_level.txt
dscontexai-1.1.0.dist-info/RECORD
